podworld/__init__.py
podworld/envs/__init__.py
podworld/envs/podworld_env.py
podworld/physics/__init__.py
podworld/physics/body.py
podworld/physics/box_body.py
podworld/physics/circle_body.py
podworld/physics/phys_utils.py
podworld/physics/world.py
podworld/render/__init__.py
podworld/render/renderer.py
podworld-0.1.0.dist-info/METADATA
podworld-0.1.0.dist-info/RECORD
podworld-0.1.0.dist-info/WHEEL
podworld-0.1.0.dist-info/top_level.txt
