Metadata-Version: 2.1
Name: podworld
Version: 0.1.0
Summary: 2D partially observable dynamic world for RL experiments
Home-page: https://github.com/sytelus/podworld
Author: Shital Shah
Author-email: shitals@microsoft.com
License: MIT
Platform: UNKNOWN
Classifier: Programming Language :: Python :: 3
Classifier: License :: OSI Approved :: MIT License
Classifier: Operating System :: OS Independent
Requires-Dist: pymunk
Requires-Dist: pygame
Requires-Dist: numpy
Requires-Dist: gym
